jupytergis_qgis/__init__.py
jupytergis_qgis/_version.py
jupytergis_qgis/handlers.py
jupytergis_qgis/qgis_loader.py
jupytergis_qgis/qgis_ydoc.py
jupytergis_qgis/tests/__init__.py
jupytergis_qgis/tests/test_qgis.py
jupytergis_qgis/tests/files/project0.qgs
jupytergis_qgis-0.11.1.data/data/etc/jupyter/jupyter_server_config.d/jupytergis_qgis.json
jupytergis_qgis-0.11.1.data/data/share/jupyter/labextensions/@jupytergis/jupytergis-qgis/package.json
jupytergis_qgis-0.11.1.data/data/share/jupyter/labextensions/@jupytergis/jupytergis-qgis/schemas/@jupytergis/jupytergis-qgis/package.json.orig
jupytergis_qgis-0.11.1.data/data/share/jupyter/labextensions/@jupytergis/jupytergis-qgis/schemas/@jupytergis/jupytergis-qgis/qgisplugin.json
jupytergis_qgis-0.11.1.data/data/share/jupyter/labextensions/@jupytergis/jupytergis-qgis/static/234.289502f2f5fca279c845.js
jupytergis_qgis-0.11.1.data/data/share/jupyter/labextensions/@jupytergis/jupytergis-qgis/static/4.58e727bd5f18ac6d1689.js
jupytergis_qgis-0.11.1.data/data/share/jupyter/labextensions/@jupytergis/jupytergis-qgis/static/432.8b7eadb127851128d478.js
jupytergis_qgis-0.11.1.data/data/share/jupyter/labextensions/@jupytergis/jupytergis-qgis/static/remoteEntry.826b1f7429aad46d6213.js
jupytergis_qgis-0.11.1.data/data/share/jupyter/labextensions/@jupytergis/jupytergis-qgis/static/style.js
jupytergis_qgis-0.11.1.data/data/share/jupyter/labextensions/@jupytergis/jupytergis-qgis/static/third-party-licenses.json
jupytergis_qgis-0.11.1.data/data/share/jupyter/labextensions/@jupytergis/jupytergis-qgis/install.json
jupytergis_qgis-0.11.1.dist-info/METADATA
jupytergis_qgis-0.11.1.dist-info/WHEEL
jupytergis_qgis-0.11.1.dist-info/entry_points.txt
jupytergis_qgis-0.11.1.dist-info/licenses/LICENSE
jupytergis_qgis-0.11.1.dist-info/RECORD
